investfiap_package_denise_vitoriano-0.1.dist-info/licenses/LICENSE
investimentos/__init__.py
investimentos/investimentos.py
investfiap_package_denise_vitoriano-0.1.dist-info/METADATA
investfiap_package_denise_vitoriano-0.1.dist-info/WHEEL
investfiap_package_denise_vitoriano-0.1.dist-info/top_level.txt
investfiap_package_denise_vitoriano-0.1.dist-info/RECORD
